morsely/__init__.py
morsely/morse_decoder.py
morsely/morse_encoder.py
morsely/morse_utils.py
tests/__init__.py
tests/t_utility.py
tests/test_decoder.py
tests/test_encoder.py
morsely-0.0.3.dist-info/LICENSE
morsely-0.0.3.dist-info/METADATA
morsely-0.0.3.dist-info/WHEEL
morsely-0.0.3.dist-info/top_level.txt
morsely-0.0.3.dist-info/RECORD
