Metadata-Version: 2.2
Name: morsely
Version: 0.0.3
License-File: LICENSE
Requires-Dist: numpy>=2.1
Requires-Dist: scipy>=1.15
Dynamic: description
Dynamic: description-content-type
Dynamic: requires-dist
